{
  "$schema": "https://developer.microsoft.com/json-schemas/spfx-build/package-solution.schema.json",
  "solution": {
    "name": "teste-client-side-solution",
    "id": "d8286360-a2ec-4201-b622-6dfc3fdeda1b",
    "version": "1.0.0.0",
    "includeClientSideAssets": true,
    "skipFeatureDeployment": true,
    "isDomainIsolated": false,
    "developer": {
      "name": "",
      "websiteUrl": "",
      "privacyUrl": "",
      "termsOfUseUrl": "",
      "mpnId": "Undefined-1.17.4"
    },
    "metadata": {
      "shortDescription": {
        "default": "Teste description"
      },
      "longDescription": {
        "default": "Teste description"
      },
      "screenshotPaths": [],
      "videoUrl": "",
      "categories": []
    },
    "features": [
      {
        "title": "teste Feature",
        "description": "The feature that activates elements of the teste solution.",
        "id": "5f11b687-d709-4e8e-845a-aa5cb049018b",
        "version": "1.0.0.0"
      }
    ]
  },
  "paths": {
    "zippedPackage": "solution/teste.sppkg"
  }
}
